karellen/nomw/__init__.py
karellen/nomw/__main__.py
karellen/nomw/app.py
karellen/nomw/utils.py
nomw-0.0.1.dev20240303214017.dist-info/METADATA
nomw-0.0.1.dev20240303214017.dist-info/WHEEL
nomw-0.0.1.dev20240303214017.dist-info/entry_points.txt
nomw-0.0.1.dev20240303214017.dist-info/namespace_packages.txt
nomw-0.0.1.dev20240303214017.dist-info/top_level.txt
nomw-0.0.1.dev20240303214017.dist-info/zip-safe
nomw-0.0.1.dev20240303214017.dist-info/RECORD
