Metadata-Version: 2.1
Name: nomw
Version: 0.0.1.dev20240303214017
Summary: Node-On-My-Watch (NOMW) is a utility for keeping K8S EC2 nodes fresh by killing them off while ensuring the running workload remains stable
Home-page: https://github.com/karellen/node-on-my-watch
Author: Karellen, Inc.
Author-email: supervisor@karellen.co
Maintainer: Karellen, Inc., Arcadiy Ivanov
Maintainer-email: supervisor@karellen.co,arcadiy@karellen.co
License: Apache License, Version 2.0
Project-URL: Bug Tracker, https://github.com/karellen/node-on-my-watch/issues
Project-URL: Documentation, https://github.com/karellen/node-on-my-watch/
Project-URL: Source Code, https://github.com/karellen/node-on-my-watch/
Keywords: kubernetes k8s kube AWS node
Classifier: License :: OSI Approved :: Apache Software License
Classifier: Programming Language :: Python :: 3.9
Classifier: Programming Language :: Python :: 3.10
Classifier: Programming Language :: Python :: 3.11
Classifier: Programming Language :: Python :: 3.12
Classifier: Operating System :: MacOS :: MacOS X
Classifier: Operating System :: POSIX
Classifier: Operating System :: POSIX :: Linux
Classifier: Environment :: Console
Classifier: Topic :: Utilities
Classifier: Topic :: System :: Monitoring
Classifier: Topic :: System :: Distributed Computing
Classifier: Topic :: System :: Clustering
Classifier: Topic :: System :: Networking
Classifier: Intended Audience :: System Administrators
Classifier: Intended Audience :: Developers
Classifier: Development Status :: 4 - Beta
Requires-Python: >=3.9
Requires-Dist: boto3 ~=1.34
Requires-Dist: coloredlogs ~=15.0
Requires-Dist: gevent >=21.1.2
Requires-Dist: json-log-formatter ~=0.3
Requires-Dist: kubernetes ~=29.0
Requires-Dist: platformdirs ~=4.2
Requires-Dist: requests ~=2.25
